.gitlab-ci.yml
.travis.yml
CHANGES.rst
CONTRIBUTORS.rst
DEVELOP.rst
Gruntfile.js
LICENSE.GPL
LICENSE.rst
MANIFEST.in
README.rst
package-lock.json
package.json
requirements.txt
setup.cfg
setup.py
docs/index.rst
src/collective/__init__.py
src/collective.expandcollapse.tile.egg-info/PKG-INFO
src/collective.expandcollapse.tile.egg-info/SOURCES.txt
src/collective.expandcollapse.tile.egg-info/dependency_links.txt
src/collective.expandcollapse.tile.egg-info/entry_points.txt
src/collective.expandcollapse.tile.egg-info/namespace_packages.txt
src/collective.expandcollapse.tile.egg-info/not-zip-safe
src/collective.expandcollapse.tile.egg-info/requires.txt
src/collective.expandcollapse.tile.egg-info/top_level.txt
src/collective/expandcollapse/__init__.py
src/collective/expandcollapse/tile/__init__.py
src/collective/expandcollapse/tile/configure.zcml
src/collective/expandcollapse/tile/interfaces.py
src/collective/expandcollapse/tile/setuphandlers.py
src/collective/expandcollapse/tile/testing.py
src/collective/expandcollapse/tile/upgrades.py
src/collective/expandcollapse/tile/upgrades.zcml
src/collective/expandcollapse/tile/browser/__init__.py
src/collective/expandcollapse/tile/browser/configure.zcml
src/collective/expandcollapse/tile/browser/static/expand_collapse.js
src/collective/expandcollapse/tile/browser/static/styles.scss
src/collective/expandcollapse/tile/browser/static/dist/expand_collapse_compiled.js
src/collective/expandcollapse/tile/browser/static/dist/expand_collapse_compiled.js.map
src/collective/expandcollapse/tile/browser/static/dist/expand_collapse_compiled.min.js
src/collective/expandcollapse/tile/browser/static/dist/styles.css
src/collective/expandcollapse/tile/browser/static/dist/styles.css.map
src/collective/expandcollapse/tile/locales/README.rst
src/collective/expandcollapse/tile/locales/__init__.py
src/collective/expandcollapse/tile/locales/collective.expandcollapse.tile.pot
src/collective/expandcollapse/tile/locales/update.py
src/collective/expandcollapse/tile/locales/update.sh
src/collective/expandcollapse/tile/locales/en/LC_MESSAGES/collective.expandcollapse.tile.po
src/collective/expandcollapse/tile/profiles/default/browserlayer.xml
src/collective/expandcollapse/tile/profiles/default/metadata.xml
src/collective/expandcollapse/tile/profiles/default/registry.xml
src/collective/expandcollapse/tile/profiles/uninstall/browserlayer.xml
src/collective/expandcollapse/tile/profiles/uninstall/registry.xml
